[
  {
    "img": "https://mtlnn.com/logo/zaimer2.png",
    "link": "https://affpipe.click/kbMGLQDj",
    "price": "30 000 ₽"
  },
  {
    "img": "https://mtlnn.com/logo/moneyman.png",
    "link": "https://affpipe.click/dCvhRqbn",
    "price": "100 000 ₽"
  },
  {
    "img": "https://mtlnn.com/logo/webzaim-logo.png",
    "link": "https://affpipe.click/P75L457H",
    "price": "30 000 ₽"
  },
  {
    "img": "https://mtlnn.com/logo/mig_credit.png",
    "link": "https://affpipe.click/N4RSW3Ks",
    "price": "100 000 ₽"
  },
  {
    "img": "https://mtlnn.com/logo/krediska.png",
    "link": "https://affpipe.click/k66X4W37",
    "price": "30 000 ₽"
  },
  {
    "img": "https://mtlnn.com/logo/turbozaim.jpg",
    "link": "https://affpipe.click/1QkFfnNG",
    "price": "50 000 ₽"
  },
  {
    "img": "https://mtlnn.com/logo/joymoney.png",
    "link": "https://affpipe.click/79JPPjrK",
    "price": "100 000 ₽"
  },
  {
    "img": "https://mtlnn.com/logo/lime.png",
    "link": "https://affpipe.click/YJv2HQF9",
    "price": "100 000 ₽"
  },
  {
    "img": "https://mtlnn.com/logo/zaymigo-logo.png",
    "link": "https://affpipe.click/XGzrFp8G",
    "price": "30 000 ₽"
  },
  {
    "img": "https://mtlnn.com/logo/do_zarplati.png",
    "link": "https://affpipe.click/b6qvNRkj",
    "price": "100 000 ₽"
  }
]
